push2HAL/__init__.py
push2HAL/aofr.xsd
push2HAL/default.py
push2HAL/execHAL.py
push2HAL/json2hal.py
push2HAL/libHAL.py
push2HAL/misc.py
push2HAL/pdf2hal.py
push2HAL/version.py
push2hal-0.3.9.dist-info/METADATA
push2hal-0.3.9.dist-info/WHEEL
push2hal-0.3.9.dist-info/entry_points.txt
push2hal-0.3.9.dist-info/licenses/AUTHORS
push2hal-0.3.9.dist-info/licenses/LICENSE
push2hal-0.3.9.dist-info/RECORD
