Metadata-Version: 2.1
Name: push2HAL
Version: 0.3.9
Summary: Tools to push content to HAL repo
Project-URL: Homepage, https://github.com/luclaurent/push2HAL
Project-URL: Repository, https://github.com/luclaurent/push2HAL.git
Project-URL: Issues, https://github.com/luclaurent/push2HAL/issues
Author-email: Luc LAURENT <luc.laurent@lecnam.net>
License:                     GNU GENERAL PUBLIC LICENSE
License-File: AUTHORS
License-File: LICENSE
Keywords: HAL,OA,Open-Access,push,tei
Classifier: License :: OSI Approved :: GNU General Public License v3 (GPLv3)
Classifier: Operating System :: Unix
Classifier: Programming Language :: Python :: 3
Requires-Python: >=3.8
Requires-Dist: lxml
Requires-Dist: pdftitle
Requires-Dist: pycountry
Requires-Dist: pymupdf
Requires-Dist: python-stdnum
Requires-Dist: requests
Requires-Dist: unidecode
